README.md
setup.cfg
setup.py
gb_prob_dist/Binomialdistribution.py
gb_prob_dist/Gaussiandistribution.py
gb_prob_dist/Generaldistribution.py
gb_prob_dist/__init__.py
gb_prob_dist.egg-info/PKG-INFO
gb_prob_dist.egg-info/SOURCES.txt
gb_prob_dist.egg-info/dependency_links.txt
gb_prob_dist.egg-info/not-zip-safe
gb_prob_dist.egg-info/top_level.txt