Metadata-Version: 1.0
Name: gb-prob-dist
Version: 0.1
Summary: Gaussian and Binomial Probability Distributions
Home-page: UNKNOWN
Author: Depei Zhang
Author-email: dpz.zhang@gmail.com
License: UNKNOWN
Platform: UNKNOWN
